deeprec/__init__.py
deeprec/data/__init__.py
deeprec/data/load_dataset.py
deeprec/data/retail/__init__.py
deeprec/models/__init__.py
deeprec/models/deepfm.py
deeprec/models/layers.py
deeprec/training/__init__.py
deeprec/training/trainer.py
deep_rec-0.0.5.dist-info/LICENSE
deep_rec-0.0.5.dist-info/METADATA
deep_rec-0.0.5.dist-info/WHEEL
deep_rec-0.0.5.dist-info/top_level.txt
deep_rec-0.0.5.dist-info/RECORD
