Metadata-Version: 2.1
Name: deep-rec
Version: 0.0.5
Summary: PyTorch implementation of Deep Factorization Machine Models
Home-page: https://github.com/jaisenbe58r/deep-rec
Author: Jaime Sendra Berenguer
Author-email: jaimesendraberenguer@gmail.com
License: UNKNOWN
Platform: any
Classifier: Development Status :: 3 - Alpha
Classifier: Intended Audience :: Developers
Classifier: Topic :: Software Development :: Build Tools
Classifier: License :: OSI Approved :: MIT License
Classifier: Programming Language :: Python :: 3
Classifier: Programming Language :: Python :: 3.6
Classifier: Programming Language :: Python :: 3.7
Classifier: Programming Language :: Python :: 3.8
Classifier: Operating System :: Microsoft :: Windows
Classifier: Operating System :: POSIX
Classifier: Operating System :: Unix
Classifier: Operating System :: MacOS
Classifier: Programming Language :: Python :: 3.7
Classifier: Topic :: Scientific/Engineering
Classifier: Topic :: Scientific/Engineering :: Artificial Intelligence
Classifier: Topic :: Scientific/Engineering :: Information Analysis
Classifier: Topic :: Scientific/Engineering :: Image Recognition
Requires-Python: >=3.6
Requires-Dist: pandas
Requires-Dist: numpy
Requires-Dist: wandb (==0.10.27)
Requires-Dist: tqdm
Requires-Dist: scikit-learn
Requires-Dist: setuptools
